blobhub
