Metadata-Version: 2.1
Name: blobhub
Version: 0.1.5
Summary: BlobHub Python SDK
Home-page: https://blobhub.io/
Author: BlobHub
Author-email: developers@blobhub.io
License: MIT
Keywords: blobhub,data,onnx,git,graph
Platform: UNKNOWN
Classifier: Development Status :: 3 - Alpha
Classifier: Intended Audience :: Developers
Classifier: Topic :: Software Development :: Build Tools
Classifier: License :: OSI Approved :: MIT License
Classifier: Programming Language :: Python :: 3.6
Classifier: Programming Language :: Python :: 3.7
